main.py
putio_mcp_server-0.1.3.dist-info/licenses/LICENSE
putio_mcp_server-0.1.3.dist-info/METADATA
putio_mcp_server-0.1.3.dist-info/WHEEL
putio_mcp_server-0.1.3.dist-info/entry_points.txt
putio_mcp_server-0.1.3.dist-info/top_level.txt
putio_mcp_server-0.1.3.dist-info/RECORD
