Metadata-Version: 2.4
Name: putio-mcp-server
Version: 0.1.3
Summary: MCP server for interacting with put.io
Requires-Python: >=3.12
License-File: LICENSE
Requires-Dist: mcp>=1.6.0
Requires-Dist: putio-py>=8.8.0
Dynamic: license-file
